mcps/__init__.py
mcps/client.py
mcps/skeleton.py
mcps/agents/__init__.py
mcps/agents/agent_manager.py
mcps/agents/discovery/__init__.py
mcps/agents/discovery/base.py
mcps/agents/discovery/local.py
mcps/agents/lifecycle/__init__.py
mcps/agents/lifecycle/base.py
mcps/agents/lifecycle/standard.py
mcps/agents/runtime/__init__.py
mcps/agents/runtime/base.py
mcps/agents/runtime/docker.py
mcps/agents/runtime/python.py
mcps/agents/runtime/resource.py
mcps/cli/__init__.py
mcps/cli/base.py
mcps/cli/commands/basic.py
mcps/cli/commands/agent/__init__.py
mcps/cli/commands/agent/discovery.py
mcps/cli/commands/agent/lifecycle.py
mcps/cli/commands/agent/main.py
mcps/cli/plugins/manager.py
mcps/config/__init__.py
mcps/config/base.py
mcps/config/cache.py
mcps/config/nacos_config.py
mcps/core/__init__.py
mcps/core/auth/__init__.py
mcps/core/auth/api_key.py
mcps/core/auth/base.py
mcps/core/exceptions/__init__.py
mcps/core/exceptions/base.py
mcps/core/transports/__init__.py
mcps/core/transports/base.py
mcps/core/transports/http.py
mcps/monitoring/__init__.py
mcps/monitoring/base.py
mcps/monitoring/memory.py
mcps/monitoring/tracing.py
mcps/services/__init__.py
mcps/services/discovery/__init__.py
mcps/services/discovery/base.py
mcps/services/discovery/registry_based.py
mcps/services/governance/__init__.py
mcps/services/governance/base.py
mcps/services/registry/__init__.py
mcps/services/registry/base.py
mcps/services/registry/memory.py
mcps/services/registry/vector.py
mcps/tools/__init__.py
mcps/tools/base.py
mcps/tools/local/memory.py
mcps/tools/remote/http.py
mcps/utils/__init__.py
mcps/utils/base.py
mcps/utils/cache/__init__.py
mcps/utils/cache/log.py
mcps/utils/cache/message.py
mcps/utils/crypto/aes.py
mcps/utils/schemas/json.py
mcps/utils/state/memory.py
mcps-0.1.dev12.dist-info/licenses/LICENSE.txt
mcps-0.1.dev12.dist-info/METADATA
mcps-0.1.dev12.dist-info/WHEEL
mcps-0.1.dev12.dist-info/entry_points.txt
mcps-0.1.dev12.dist-info/top_level.txt
mcps-0.1.dev12.dist-info/RECORD
