Metadata-Version: 2.4
Name: mcps
Version: 0.1.dev12
Summary: Multi-Component Platform System (MCPS) - A framework for managing distributed services and agents
Home-page: https://github.com/ceresman/mcps/
Author: Winshare Tom
Author-email: tanwenxuan@ceresman.com
License: MIT
Project-URL: Documentation, https://github.com/ceresman/mcps/tree/develop/docs
Project-URL: Source, https://github.com/ceresman/mcps/
Project-URL: Tracker, https://github.com/ceresman/mcps/issues
Platform: any
Classifier: Development Status :: 4 - Beta
Classifier: Programming Language :: Python
License-File: LICENSE.txt
Requires-Dist: importlib-metadata; python_version < "3.8"
Requires-Dist: sentence-transformers>=2.2.0
Requires-Dist: jsonschema>=4.17.0
Requires-Dist: cryptography>=3.4.0
Requires-Dist: requests>=2.25.0
Provides-Extra: testing
Requires-Dist: setuptools; extra == "testing"
Requires-Dist: pytest; extra == "testing"
Requires-Dist: pytest-cov; extra == "testing"
Requires-Dist: numpy; extra == "testing"
Dynamic: license-file
